NEURON-UI
README.rst
setup.py
neuron_ui/__init__.py
neuron_ui/analysis.py
neuron_ui/cell_builder.py
neuron_ui/neuron_geometries_utils.py
neuron_ui/neuron_geppetto.py
neuron_ui/neuron_menu.py
neuron_ui/neuron_utils.py
neuron_ui/point_process.py
neuron_ui/run_control.py
neuron_ui/sample_models.py
neuron_ui/singleton.py
neuron_ui/space_plot.py
neuron_ui.egg-info/PKG-INFO
neuron_ui.egg-info/SOURCES.txt
neuron_ui.egg-info/dependency_links.txt
neuron_ui.egg-info/requires.txt
neuron_ui.egg-info/top_level.txt
neuron_ui/models/CA3_pyramidal.py
neuron_ui/models/PTcell.hoc
neuron_ui/models/PTcell.py
neuron_ui/models/__init__.py
neuron_ui/models/ball_and_stick.py
neuron_ui/models/geo-cell1zr.hoc
neuron_ui/models/ring.py
neuron_ui/models/simple_cell.py
neuron_ui/models/simple_network_old.py
neuron_ui/models/verysimple_cell.py