Metadata-Version: 1.1
Name: neuron-ui
Version: 0.0.0.1
Summary: User interface for NEURON based on web technologies and Jupyter
Home-page: https://github.com/MetaCell/NEURON-UI
Author: MetaCell
Author-email: info@metacell.us
License: MIT
Platform: UNKNOWN
Classifier: Development Status :: 3 - Alpha
Classifier: Intended Audience :: Science/Research
Classifier: Topic :: Scientific/Engineering :: Visualization
Classifier: License :: OSI Approved :: MIT License
Classifier: Programming Language :: Python :: 2
Classifier: Programming Language :: Python :: 2.6
Classifier: Programming Language :: Python :: 2.7
Classifier: Programming Language :: Python :: 3
Classifier: Programming Language :: Python :: 3.3
Classifier: Programming Language :: Python :: 3.4
